{"stats":{"minecraft:picked_up":{"minecraft:white_bed":1,"minecraft:wheat_seeds":1},"minecraft:custom":{"minecraft:jump":61,"minecraft:time_since_rest":5986,"minecraft:walk_on_water_one_cm":170,"minecraft:deaths":1,"minecraft:crouch_one_cm":136,"minecraft:sprint_one_cm":22108,"minecraft:play_time":8786,"minecraft:damage_taken":310,"minecraft:time_since_death":6391,"minecraft:walk_one_cm":28172,"minecraft:sneak_time":42,"minecraft:total_world_time":8786,"minecraft:fall_one_cm":1286,"minecraft:fly_one_cm":8322,"minecraft:open_chest":4},"minecraft:used":{"tombstone:gift":2},"minecraft:killed_by":{"creeperoverhaul:spruce_creeper":1},"minecraft:mined":{"minecraft:large_fern":3,"minecraft:grass":1,"minecraft:spruce_leaves":3,"minecraft:white_bed":1}},"DataVersion":3120}